{
  "lock_version": 1,
  "position": 83,
  "publish": true,
  "ref_id": "c50d54d3c4d64ff2919ba324039eda23",
  "title": "Special Events",
  "display_string": "Special Events",
  "restrictions_apply": false,
  "created_by": "admin",
  "last_modified_by": "pgalligan",
  "create_time": "2014-12-06T09:30:06Z",
  "system_mtime": "2019-01-15T19:33:16Z",
  "user_mtime": "2017-02-19T18:24:47Z",
  "suppressed": false,
  "level": "file",
  "jsonmodel_type": "archival_object",
  "external_ids": [
    {
      "external_id": "1171971",
      "source": "Archivists Toolkit Database::RESOURCE_COMPONENT",
      "created_by": "pgalligan",
      "last_modified_by": "pgalligan",
      "create_time": "2017-02-19T18:24:47Z",
      "system_mtime": "2017-02-19T18:24:47Z",
      "user_mtime": "2017-02-19T18:24:47Z",
      "jsonmodel_type": "external_id"
    }
  ],
  "subjects": [],
  "linked_events": [],
  "extents": [],
  "dates": [],
  "external_documents": [],
  "rights_statements": [],
  "linked_agents": [],
  "ancestors": [
    {
      "ref": "/repositories/2/archival_objects/285811",
      "level": "file"
    },
    {
      "ref": "/repositories/2/resources/537",
      "level": "series"
    }
  ],
  "instances": [
    {
      "lock_version": 0,
      "created_by": "pgalligan",
      "last_modified_by": "pgalligan",
      "create_time": "2017-02-19T18:24:47Z",
      "system_mtime": "2017-02-19T18:24:47Z",
      "user_mtime": "2017-02-19T18:24:47Z",
      "instance_type": "mixed materials",
      "jsonmodel_type": "instance",
      "is_representative": false,
      "sub_container": {
        "lock_version": 0,
        "indicator_2": "639",
        "created_by": "pgalligan",
        "last_modified_by": "pgalligan",
        "create_time": "2017-02-19T18:24:47Z",
        "system_mtime": "2017-02-19T18:24:47Z",
        "user_mtime": "2017-02-19T18:24:47Z",
        "type_2": "folder",
        "jsonmodel_type": "sub_container",
        "top_container": {
          "ref": "/repositories/2/top_containers/49231"
        }
      }
    }
  ],
  "notes": [
    {
      "subnotes": [
        {
          "content": "Arrangements and guest lists for the following special events: New York Legislators, 4/17/59 Dona Sara Kubitschek, 4/12/59\n\n",
          "publish": true,
          "jsonmodel_type": "note_text"
        }
      ],
      "jsonmodel_type": "note_multipart",
      "persistent_id": "07a30a23dabe578a6e18a3e6358f0658",
      "label": "Scope and Contents note",
      "type": "scopecontent",
      "publish": true
    }
  ],
  "uri": "/repositories/2/archival_objects/285894",
  "repository": {
    "ref": "/repositories/2"
  },
  "resource": {
    "ref": "/repositories/2/resources/537"
  },
  "parent": {
    "ref": "/repositories/2/archival_objects/285811"
  },
  "has_unpublished_ancestor": false
}