{
    "create_time": "2014-12-06T02:30:08Z",
    "created_by": "admin",
    "external_documents": [],
    "external_ids": [
        {
            "create_time": "2014-12-06T02:30:08Z",
            "created_by": "admin",
            "external_id": "323",
            "jsonmodel_type": "external_id",
            "last_modified_by": "admin",
            "source": "Archivists Toolkit Database::SUBJECT",
            "system_mtime": "2014-12-06T02:30:08Z",
            "user_mtime": "2014-12-06T02:30:08Z"
        }
    ],
    "is_linked_to_published_record": true,
    "jsonmodel_type": "subject",
    "last_modified_by": "admin",
    "lock_version": 307,
    "publish": true,
    "source": "lcsh",
    "system_mtime": "2018-12-11T20:41:03Z",
    "terms": [
        {
            "create_time": "2014-12-06T02:30:09Z",
            "created_by": "admin",
            "jsonmodel_type": "term",
            "last_modified_by": "admin",
            "lock_version": 0,
            "system_mtime": "2014-12-06T02:30:09Z",
            "term": "Developing countries",
            "term_type": "topical",
            "uri": "/terms/271",
            "user_mtime": "2014-12-06T02:30:09Z",
            "vocabulary": "/vocabularies/1"
        }
    ],
    "title": "Developing countries",
    "uri": "/subjects/265",
    "used_within_published_repositories": [
        "/repositories/2"
    ],
    "used_within_repositories": [
        "/repositories/2"
    ],
    "user_mtime": "2014-12-06T02:30:08Z",
    "vocabulary": "/vocabularies/1"
}